<?xml version="1.0" encoding="utf-16"?>
<ZL_OBJECT CHECKSUM="5D848D00D5A0BAEFB8476BDD85615CE3" CONNECTOR="5079624B82531D63E1000000AC120173" NAME="YGPLDS_CACHE" TYPE="TABL" VERSION="1.0">
 <DIRECTORY DEVCLASS="YGPL-DATA_STORE" MASTERLANG="E"/>
 <RAW>
  <A0_MAINDATA TABCLASS="TRANSP" CLIDEP="X" MAINFLAG="N" CONTFLAG="L" EXCLASS="1">
   <TECHNICAL_SETTINGS TABKAT="0" TABART="USER" BUFALLOW="N"/>
  </A0_MAINDATA>
  <FIELDS>
   <ITEM FIELDNAME="MANDT" POSITION="0001" KEYFLAG="X" ROLLNAME="MANDT" ADMINFIELD="0" INTTYPE="C" INTLEN="000006" NOTNULL="X" DOMNAME="MANDT" HEADLEN="03" SCRLEN1="10" SCRLEN2="15" SCRLEN3="20" DTELMASTER="D" DATATYPE="CLNT" LENG="000003" OUTPUTLEN="000003" ENTITYTAB="T000" MASK="  CLNTE" DOMNAME3L="MANDT" COMPTYPE="E" DEFFDNAME="CLIENT"/>
   <ITEM FIELDNAME="ID" POSITION="0002" KEYFLAG="X" ROLLNAME="GUID_32" ADMINFIELD="0" INTTYPE="C" INTLEN="000064" NOTNULL="X" DOMNAME="SYSUUID_C" HEADLEN="07" SCRLEN1="10" SCRLEN2="15" SCRLEN3="20" DTELMASTER="D" DATATYPE="CHAR" LENG="000032" OUTPUTLEN="000032" MASK="  CHARE" DOMNAME3L="SYSUUID_C" COMPTYPE="E"/>
   <ITEM FIELDNAME="RELID" POSITION="0003" KEYFLAG="X" ROLLNAME="INDX_RELID" ADMINFIELD="0" INTTYPE="C" INTLEN="000004" NOTNULL="X" DOMNAME="SYCHAR02" HEADLEN="10" SCRLEN1="10" SCRLEN2="10" SCRLEN3="10" DATATYPE="CHAR" LENG="000002" OUTPUTLEN="000002" MASK="  CHARE" DOMNAME3L="SYCHAR02" COMPTYPE="E"/>
   <ITEM FIELDNAME="SRTF2" POSITION="0004" KEYFLAG="X" ROLLNAME="INDX_SRTF2" ADMINFIELD="0" INTTYPE="X" INTLEN="000004" NOTNULL="X" DOMNAME="SYBIN4" HEADLEN="55" SCRLEN1="10" SCRLEN2="15" SCRLEN3="20" DTELMASTER="D" DATATYPE="INT4" LENG="000010" OUTPUTLEN="000010" SIGNFLAG="X" MASK="  INT4E" DOMNAME3L="SYBIN4" COMPTYPE="E"/>
   <ITEM FIELDNAME="CLUSTR" POSITION="0005" ROLLNAME="INDX_CLSTR" ADMINFIELD="0" INTTYPE="X" INTLEN="000002" DOMNAME="SYBIN2" HEADLEN="20" SCRLEN1="10" SCRLEN2="15" SCRLEN3="20" DATATYPE="INT2" LENG="000005" OUTPUTLEN="000005" SIGNFLAG="X" MASK="  INT2E" DOMNAME3L="SYBIN2" COMPTYPE="E"/>
   <ITEM FIELDNAME="CLUSTD" POSITION="0006" ADMINFIELD="0" INTTYPE="X" INTLEN="032000" DATATYPE="LRAW" LENG="032000" MASK="  LRAW">
    <TEXTS>
     <ITEM LANGU="E" SHORT_TXT="Raw storage (max value 32Ko)"/>
    </TEXTS>
   </ITEM>
  </FIELDS>
  <TEXTS>
   <ITEM LANGU="E" SHORT_TXT="For cache storage in Shared Memory (no DB Use)"/>
  </TEXTS>
 </RAW>
</ZL_OBJECT>
