<?xml version="1.0" encoding="utf-16"?>
<ZL_OBJECT CHECKSUM="B15D3A70DD32342DD55E8209481CEF65" CODE_SIGNATURE="D7AC899690217175B2E8A590F9277372" CONNECTOR="39AC0A4B07A5A05AE1000000AC120173" NAME="YGPLIDBA_CHECK_TABLES" TYPE="INTF" VERSION="1.01">
 <DIRECTORY DEVCLASS="YGPL-DBA" MASTERLANG="E"/>
 <RAW>
  <A0_MAINDATA VERSION="1" LANGU="E" EXPOSURE="2" STATE="1" UNICODE="X">
   <TEXTS>
    <ITEM LANG="E" TEXT="DBA tools - Check table consistency">U1&amp;FUNCTIONALITY&amp;
ASAllow to activate (compile) a components.
U1&amp;RELATIONS&amp;
AS
U1&amp;EXAMPLE&amp;
AS
U1&amp;HINTS&amp;
AS
U1&amp;FURTHER_SOURCES_OF_INF&amp;
AS</ITEM>
   </TEXTS>
  </A0_MAINDATA>
  <ALIASES>
   <ITEM CMPNAME="DO_CHECK" EXPOSURE="2" CMPTYPE="1" REFCLSNAME="YGPLIDBA_CHECK_GEN" REFCMPNAME="DO_CHECK"/>
   <ITEM CMPNAME="RESET" EXPOSURE="2" CMPTYPE="1" REFCLSNAME="YGPLIDBA_CHECK_GEN" REFCMPNAME="RESET"/>
   <ITEM CMPNAME="SET_LIST" EXPOSURE="2" CMPTYPE="1" REFCLSNAME="YGPLIDBA_CHECK_GEN" REFCMPNAME="SET_LIST"/>
   <ITEM CMPNAME="TD_TABLE_NAME" EXPOSURE="2" CMPTYPE="3" REFCLSNAME="YGPL_DBA_TYPESPOOL" REFCMPNAME="TD_TABLE_NAME"/>
   <ITEM CMPNAME="TI_OBJECT_SIZE" EXPOSURE="2" CMPTYPE="3" REFCLSNAME="YGPL_DBA_INTERFACES" REFCMPNAME="TI_OBJECT_SIZE"/>
   <ITEM CMPNAME="TI_OBJECT_STATISTICS" EXPOSURE="2" CMPTYPE="3" REFCLSNAME="YGPL_DBA_INTERFACES" REFCMPNAME="TI_OBJECT_STATISTICS"/>
   <ITEM CMPNAME="TI_TABLE_LIST" EXPOSURE="2" CMPTYPE="3" REFCLSNAME="YGPL_DBA_INTERFACES" REFCMPNAME="TI_TABLE_LIST"/>
   <ITEM CMPNAME="TR_SIZE" EXPOSURE="2" CMPTYPE="3" REFCLSNAME="YGPL_DBA_TYPESPOOL" REFCMPNAME="TR_SIZE"/>
   <ITEM CMPNAME="TT_COMPKEYS" EXPOSURE="2" CMPTYPE="3" REFCLSNAME="YGPL_DBA_TYPESPOOL" REFCMPNAME="TT_COMPKEYS"/>
  </ALIASES>
  <ATTRIBUTS>
   <ITEM CMPNAME="CHECK_LOG" EXPOSURE="2" STATE="1" ATTRDONLY="X" TYPTYPE="1" TYPE="TT_TABLES_CHECK_LOG"/>
  </ATTRIBUTS>
  <INTERFACES>
   <ITEM REFCLSNAME="YGPLIDBA_CHECK_GEN" STATE="1"/>
   <ITEM REFCLSNAME="YGPL_DBA_INTERFACES" STATE="1"/>
   <ITEM REFCLSNAME="YGPL_DBA_TYPESPOOL" STATE="1"/>
  </INTERFACES>
  <METHODS>
   <ITEM CMPNAME="GET_TABLE_CHECK_PROTOCOL" EXPOSURE="2" STATE="1">
    <TEXTS>
     <ITEM LANG="E" TEXT="Get Table&apos;s Check protocol"/>
    </TEXTS>
    <PARAMETERS>
     <ITEM SCONAME="NAME" CMPTYPE="1" PARPASSTYP="1" TYPTYPE="1" TYPE="TD_TABLE_NAME">
      <TEXTS>
       <ITEM LANG="E" TEXT="Table name, 16 characters"/>
      </TEXTS>
     </ITEM>
     <ITEM SCONAME="RESULT" CMPTYPE="1" PARDECLTYP="3" TYPTYPE="1" TYPE="TT_CHECK_LOG"/>
    </PARAMETERS>
   </ITEM>
  </METHODS>
  <TYPES>
   <ITEM CMPNAME="TT_CHECK_LOG" EXPOSURE="2" STATE="1" EDITORDER="2 " TYPTYPE="4">tt_check_log TYPE STANDARD TABLE OF trlogm WITH DEFAULT KEY
`</ITEM>
   <ITEM CMPNAME="TT_TABLES_CHECK_LOG" EXPOSURE="2" STATE="1" EDITORDER="1 " TYPTYPE="4">tt_tables_check_log TYPE STANDARD TABLE OF ygpl_dba_tables_check_result WITH DEFAULT KEY
`</ITEM>
  </TYPES>
 </RAW>
</ZL_OBJECT>
