<?xml version="1.0" encoding="utf-16"?>
<ZL_OBJECT CHECKSUM="80845B596F10192AA193F3D7BE287269" CONNECTOR="5079624B82531D63E1000000AC120173" NAME="YGPL_MT__STATUS" TYPE="DTEL" VERSION="1.0">
 <DIRECTORY DEVCLASS="YGPL-MULTITHREAD" MASTERLANG="E"/>
 <RAW>
  <A0_MAINDATA DOMNAME="YGPL_MT_DATA_STATUS" DTELMASTER="E" DATATYPE="CHAR" LENG="000001" OUTPUTLEN="000001" LOWERCASE="X" ENTITYTAB="YGPLMT_STATUS" REFKIND="D"/>
  <TEXTS>
   <ITEM LANGU="E" SHORT_TXT="Run/Job/Object Status"/>
   <ITEM LANGU="F" SHORT_TXT="Status des enregistrements"/>
  </TEXTS>
 </RAW>
</ZL_OBJECT>
